setup.cfg
setup.py
usmart_sdk/__init__.py
usmart_sdk/usmart.py
usmart_sdk.egg-info/PKG-INFO
usmart_sdk.egg-info/SOURCES.txt
usmart_sdk.egg-info/dependency_links.txt
usmart_sdk.egg-info/top_level.txt