Metadata-Version: 1.1
Name: usmart-sdk
Version: 1.0.1
Summary: USMART SDK
Home-page: https://github.com/UrbanTide/usmart-sdk-py
Author: Jacek Dudek
Author-email: jacek.dudek@urbantide.com
License: MIT
Download-URL: https://github.com/UrbanTide/usmart-sdk-py/archive/1.0.1.tar.gz
Platform: UNKNOWN
